{
    "batch_profiling": 0.01720000000204891,
    "node_scoring_per_pkt": [
        0.03029999788850546,
        0.02020000829361379,
        0.019700004486367106,
        0.018999999156221747,
        0.01889999839477241,
        0.019700004486367106,
        0.018999999156221747,
        0.018799997633323073,
        0.01920000067912042,
        0.01850000990089029
    ],
    "enclave_scoring_per_pkt": [
        0.012599994079209864,
        0.009499999578110874,
        0.007000009645707905,
        0.005699999746866524,
        0.005699999746866524,
        0.005599998985417187,
        0.00549999822396785,
        0.005399997462518513,
        0.005599998985417187,
        0.00549999822396785
    ],
    "assignments": [
        {
            "device": "IIoT-DEV-000",
            "fog_node": 0,
            "enclave": "E_0_3",
            "node_score": 4.4244,
            "enclave_score": 0.0036
        },
        {
            "device": "IIoT-DEV-001",
            "fog_node": 1,
            "enclave": "E_1_3",
            "node_score": 4.4471,
            "enclave_score": 0.0035
        },
        {
            "device": "IIoT-DEV-002",
            "fog_node": 0,
            "enclave": "E_0_3",
            "node_score": 4.4549,
            "enclave_score": -4.9891
        },
        {
            "device": "IIoT-DEV-003",
            "fog_node": 1,
            "enclave": "E_1_3",
            "node_score": 4.4706,
            "enclave_score": -4.9895
        },
        {
            "device": "IIoT-DEV-004",
            "fog_node": 2,
            "enclave": "E_2_1",
            "node_score": 4.4732,
            "enclave_score": 0.0041
        },
        {
            "device": "IIoT-DEV-005",
            "fog_node": 2,
            "enclave": "E_2_1",
            "node_score": 4.5,
            "enclave_score": -4.9878
        },
        {
            "device": "IIoT-DEV-006",
            "fog_node": 0,
            "enclave": "E_0_3",
            "node_score": 4.5056,
            "enclave_score": -4.9819
        },
        {
            "device": "IIoT-DEV-007",
            "fog_node": 1,
            "enclave": "E_1_3",
            "node_score": 4.5097,
            "enclave_score": -4.9825
        },
        {
            "device": "IIoT-DEV-008",
            "fog_node": 2,
            "enclave": "E_2_1",
            "node_score": 4.5448,
            "enclave_score": -4.9797
        },
        {
            "device": "IIoT-DEV-009",
            "fog_node": 1,
            "enclave": "E_1_3",
            "node_score": 4.5645,
            "enclave_score": -4.9754
        }
    ],
    "total_scheduler_latency": 51.20610000449233,
    "rejected_count": 0
}